pytest_resume/__init__.py
pytest_resume/plugin.py
pytest_resume-0.0.1.dist-info/LICENSE
pytest_resume-0.0.1.dist-info/METADATA
pytest_resume-0.0.1.dist-info/WHEEL
pytest_resume-0.0.1.dist-info/entry_points.txt
pytest_resume-0.0.1.dist-info/top_level.txt
pytest_resume-0.0.1.dist-info/RECORD
